web3tg/__init__.py
web3tg/main.py
web3tg/callbacks/__init__.py
web3tg/callbacks/profiles_tasks_callbacks.py
web3tg/callbacks/social_tasks_callbacks.py
web3tg/data/__init__.py
web3tg/data/save.py
web3tg/data/subloader.py
web3tg/extra/__init__.py
web3tg/extra/accounts.py
web3tg/extra/capmonster.py
web3tg/extra/ds.py
web3tg/extra/imap.py
web3tg/extra/logger.py
web3tg/extra/pandez.py
web3tg/extra/tasks.py
web3tg/extra/tw.py
web3tg/extra/web3.py
web3tg/extra/windows.py
web3tg/handlers/__init__.py
web3tg/handlers/basic_commands.py
web3tg/handlers/user_commands.py
web3tg/keyboards/__init__.py
web3tg/keyboards/fabrics.py
web3tg/middlewares/__init__.py
web3tg/middlewares/is_admin.py
web3tg/utils/__init__.py
web3tg/utils/other.py
web3tg/utils/states.py
web3tg-0.0.1.dist-info/METADATA
web3tg-0.0.1.dist-info/WHEEL
web3tg-0.0.1.dist-info/top_level.txt
web3tg-0.0.1.dist-info/RECORD
